.gitignore
LICENSE
MANIFEST.in
README.md
setup.cfg
setup.py
slingshot/__init__.py
slingshot/examples/__init__.py
slingshot/examples/simple_claim.py
slingshot/procedural_document/__init__.py
slingshot/procedural_document/core.py
slingshot/procedural_document/layers/__init__.py
slingshot/procedural_document/layers/base.py
slingshot/procedural_document/layers/models.py
slingshot/procedural_document/layers/parts.py
slingshot_lawdocs.egg-info/PKG-INFO
slingshot_lawdocs.egg-info/SOURCES.txt
slingshot_lawdocs.egg-info/dependency_links.txt
slingshot_lawdocs.egg-info/requires.txt
slingshot_lawdocs.egg-info/top_level.txt