Metadata-Version: 2.1
Name: slingshot-lawdocs
Version: 0.5.5
Summary: Slingshot is a Python library bringed on by A Mosca team for creating reproducible procedural documents for Brazilian law-suits.
Home-page: https://github.com/amosca-team/slingshot/
Author: A Mosca
Author-email: staff.amosca@gmail.com
License: MIT
Platform: UNKNOWN
Classifier: Development Status :: 3 - Alpha
Classifier: Intended Audience :: Developers
Classifier: Programming Language :: Python :: 3.7
